vizneuron/__init__.py
vizneuron/callback.py
vizneuron/memory_usage.py
vizneuron/monitor.py
vizneuron-0.0.1.dist-info/LICENSE
vizneuron-0.0.1.dist-info/METADATA
vizneuron-0.0.1.dist-info/WHEEL
vizneuron-0.0.1.dist-info/top_level.txt
vizneuron-0.0.1.dist-info/RECORD
